pyk3d/__init__.py
pyk3d/__version__.py
pyk3d/mymodule.py
pyk3d-0.0.1.dist-info/LICENSE
pyk3d-0.0.1.dist-info/WHEEL
pyk3d-0.0.1.dist-info/METADATA
pyk3d-0.0.1.dist-info/RECORD
