Metadata-Version: 2.1
Name: pyk3d
Version: 0.0.1
Summary: 
Author: Your Name
Author-email: user@example.com
Requires-Python: >=3.7,<4.0
Classifier: Programming Language :: Python :: 3
Classifier: Programming Language :: Python :: 3.7
Classifier: Programming Language :: Python :: 3.8
Classifier: Programming Language :: Python :: 3.9
